wagtail_indexnow/__init__.py
wagtail_indexnow/urls.py
wagtail_indexnow/utils.py
wagtail_indexnow/views.py
wagtail_indexnow/wagtail_hooks.py
wagtail_indexnow-0.2.0.dist-info/licenses/LICENSE
wagtail_indexnow-0.2.0.dist-info/WHEEL
wagtail_indexnow-0.2.0.dist-info/METADATA
wagtail_indexnow-0.2.0.dist-info/RECORD
