Metadata-Version: 2.4
Name: wagtail-indexnow
Version: 0.2.0
Summary: A Wagtail package to automatically submit published pages for search engine indexing
Author: Jake Howard
Requires-Python: >=3.10
Classifier: License :: OSI Approved
Classifier: License :: OSI Approved :: BSD License
Classifier: Framework :: Wagtail
Classifier: Framework :: Wagtail :: 6
Classifier: Framework :: Wagtail :: 7
Classifier: Framework :: Django
Classifier: Framework :: Django :: 4.2
Classifier: Framework :: Django :: 5.1
Classifier: Framework :: Django :: 5.2
Classifier: Development Status :: 5 - Production/Stable
Classifier: Programming Language :: Python :: 3
Classifier: Programming Language :: Python :: 3.10
Classifier: Programming Language :: Python :: 3.11
Classifier: Programming Language :: Python :: 3.12
Classifier: Programming Language :: Python :: 3.13
Classifier: Operating System :: OS Independent
Classifier: Topic :: Internet :: WWW/HTTP
Classifier: Topic :: Software Development
Classifier: Typing :: Typed
License-File: LICENSE
Requires-Dist: wagtail>=6.3
Requires-Dist: Django>=4.2
Requires-Dist: ruff ; extra == "dev"
Requires-Dist: black ; extra == "dev"
Requires-Dist: requests-mock ; extra == "dev"
Project-URL: Changelog, https://github.com/RealOrangeOne/wagtail-indexnow/releases
Project-URL: Issues, https://github.com/RealOrangeOne/wagtail-indexnow/issues
Project-URL: Source, https://github.com/RealOrangeOne/wagtail-indexnow
Provides-Extra: dev
